pyequa/__init__.py
pyequa/clozeroutines.py
pyequa/config.py
pyequa/default_config.yaml
pyequa/scenario.py
pyequa/serviceabstract.py
pyequa/servicecloze.py
pyequa-0.0.1.dist-info/METADATA
pyequa-0.0.1.dist-info/WHEEL
pyequa-0.0.1.dist-info/RECORD
